Metadata-Version: 1.1
Name: append-db
Version: 0.1.0
Summary: AppendDb
Home-page: https://github.com/kshramt/append_db
Author: kshramt
Author-email: UNKNOWN
License: UNKNOWN
Platform: UNKNOWN
Classifier: License :: OSI Approved :: GNU General Public License v3 (GPLv3)
